bloxone/__init__.py
bloxone/activetrust.py
bloxone/b1anycast.py
bloxone/b1authn.py
bloxone/b1bootstrap.py
bloxone/b1cdc.py
bloxone/b1ddi.py
bloxone/b1diagnostics.py
bloxone/b1notifications.py
bloxone/b1oph.py
bloxone/b1platform.py
bloxone/b1sw.py
bloxone/b1td.py
bloxone/b1tdc.py
bloxone/b1tddfp.py
bloxone/b1tdep.py
bloxone/b1tdfw.py
bloxone/b1tdlad.py
bloxone/b1ztp.py
bloxone/bloxone.py
bloxone/dhcputils.py
bloxone/threat_defense.py
bloxone/utils.py
bloxone/__pycache__/__init__.cpython-36.pyc
bloxone/__pycache__/__init__.cpython-38.pyc
bloxone/__pycache__/__init__.cpython-39.pyc
bloxone/__pycache__/b1anycast.cpython-36.pyc
bloxone/__pycache__/b1anycast.cpython-38.pyc
bloxone/__pycache__/b1anycast.cpython-39.pyc
bloxone/__pycache__/b1authn.cpython-36.pyc
bloxone/__pycache__/b1authn.cpython-38.pyc
bloxone/__pycache__/b1authn.cpython-39.pyc
bloxone/__pycache__/b1bootstrap.cpython-36.pyc
bloxone/__pycache__/b1bootstrap.cpython-38.pyc
bloxone/__pycache__/b1bootstrap.cpython-39.pyc
bloxone/__pycache__/b1cdc.cpython-36.pyc
bloxone/__pycache__/b1cdc.cpython-38.pyc
bloxone/__pycache__/b1cdc.cpython-39.pyc
bloxone/__pycache__/b1ddi.cpython-36.pyc
bloxone/__pycache__/b1ddi.cpython-38.pyc
bloxone/__pycache__/b1ddi.cpython-39 2.pyc
bloxone/__pycache__/b1ddi.cpython-39.pyc
bloxone/__pycache__/b1diagnostics.cpython-39.pyc
bloxone/__pycache__/b1notifications.cpython-39.pyc
bloxone/__pycache__/b1oph.cpython-36.pyc
bloxone/__pycache__/b1oph.cpython-38.pyc
bloxone/__pycache__/b1oph.cpython-39.pyc
bloxone/__pycache__/b1platform.cpython-36.pyc
bloxone/__pycache__/b1platform.cpython-38.pyc
bloxone/__pycache__/b1platform.cpython-39 2.pyc
bloxone/__pycache__/b1platform.cpython-39.pyc
bloxone/__pycache__/b1sw.cpython-36.pyc
bloxone/__pycache__/b1sw.cpython-38.pyc
bloxone/__pycache__/b1sw.cpython-39.pyc
bloxone/__pycache__/b1td.cpython-36.pyc
bloxone/__pycache__/b1td.cpython-38.pyc
bloxone/__pycache__/b1td.cpython-39.pyc
bloxone/__pycache__/b1tdc.cpython-36.pyc
bloxone-0.8.14.dist-info/LICENSE
bloxone-0.8.14.dist-info/METADATA
bloxone-0.8.14.dist-info/WHEEL
bloxone-0.8.14.dist-info/top_level.txt
bloxone-0.8.14.dist-info/RECORD
