Metadata-Version: 2.1
Name: bloxone
Version: 0.8.14
Summary: BloxOne API Wrapper Module
Home-page: https://github.com/ccmarris/python-bloxone
Author: Chris Marrison
Author-email: chris@infoblox.com
License: BSD-2-Clause
Project-URL: Documentation, https://python-bloxone.readthedocs.io/en/latest/
Project-URL: Source, https://github.com/ccmarris/python-bloxone
Project-URL: Tracker, https://github.com/ccmarris/python-bloxone/issues
Classifier: Programming Language :: Python :: 3
Classifier: License :: OSI Approved :: BSD License
Classifier: Operating System :: OS Independent
Requires-Python: >=3.7
License-File: LICENSE
Requires-Dist: requests
Requires-Dist: pyyaml
